odoo/addons/stock_delivery_note/README.rst
odoo/addons/stock_delivery_note/__init__.py
odoo/addons/stock_delivery_note/__manifest__.py
odoo/addons/stock_delivery_note/i18n/es.po
odoo/addons/stock_delivery_note/i18n/stock_delivery_note.pot
odoo/addons/stock_delivery_note/models/__init__.py
odoo/addons/stock_delivery_note/models/stock_picking.py
odoo/addons/stock_delivery_note/readme/CONTRIBUTORS.rst
odoo/addons/stock_delivery_note/readme/DESCRIPTION.rst
odoo/addons/stock_delivery_note/readme/USAGE.rst
odoo/addons/stock_delivery_note/reports/report_picking.xml
odoo/addons/stock_delivery_note/static/description/icon.png
odoo/addons/stock_delivery_note/static/description/index.html
odoo/addons/stock_delivery_note/views/stock_picking.xml
odoo12_addon_stock_delivery_note-12.0.1.0.1.dist-info/METADATA
odoo12_addon_stock_delivery_note-12.0.1.0.1.dist-info/WHEEL
odoo12_addon_stock_delivery_note-12.0.1.0.1.dist-info/top_level.txt
odoo12_addon_stock_delivery_note-12.0.1.0.1.dist-info/RECORD
